sysnet_ident/__init__.py
sysnet_ident/procedures.py
sysnet_ident/settings.py
sysnet_ident/test_procedures.py
sysnet_ident-1.0.2.dist-info/LICENSE.md
sysnet_ident-1.0.2.dist-info/METADATA
sysnet_ident-1.0.2.dist-info/WHEEL
sysnet_ident-1.0.2.dist-info/top_level.txt
sysnet_ident-1.0.2.dist-info/RECORD
