Metadata-Version: 2.1
Name: sysnet-ident
Version: 1.0.2
Summary: Identification procedures
Author-email: Data Developer <info@sysnet.cz>
License: # LICENCE PRO DOMÁCÍ POUŽITÍ (SYSNET Home Use License) v 1.0
Project-URL: Homepage, https://github.com/SYSNET-CZ/ident/tree/master/sysnet-ident
Classifier: Development Status :: 4 - Beta
Classifier: Programming Language :: Python :: 3
Classifier: License :: Free For Home Use
Classifier: Operating System :: OS Independent
Classifier: Topic :: System :: Systems Administration
Requires-Python: >=3.9
License-File: LICENSE.md
